secret_assistant/__init__.py
workflow_notification-9.28.2022.dist-info/METADATA
workflow_notification-9.28.2022.dist-info/WHEEL
workflow_notification-9.28.2022.dist-info/top_level.txt
workflow_notification-9.28.2022.dist-info/RECORD
