Metadata-Version: 2.1
Name: workflow-notification
Version: 9.28.2022
Summary: workflow-notification 
Home-page: https://github.com/Nllii/workflow-notification.git
Author: Nii Golightly
Author-email: nlli@pm.me
Classifier: Programming Language :: Python :: 3
Classifier: License :: OSI Approved :: MIT License
Classifier: Operating System :: OS Independent
